obor/__init__.py
obor/plotter/__init__.py
obor/plotter/plot_dynamic.py
obor/plotter/plot_training_history.py
obor/pruner/__init__.py
obor/pruner/prune_bbs.py
obor/pruner/prune_low_magnitude_structured.py
obor/pruner/prune_low_magnitude_unstructured.py
obor/utils/__init__.py
obor/utils/create_data_loader.py
obor/utils/test.py
obor/utils/train.py
obor-0.4.0.dist-info/LICENSE
obor-0.4.0.dist-info/METADATA
obor-0.4.0.dist-info/WHEEL
obor-0.4.0.dist-info/top_level.txt
obor-0.4.0.dist-info/RECORD
