Metadata-Version: 2.2
Name: obor
Version: 0.4.0
Summary: A package containing pytorch utilities
Author-email: doddy-s <doddy.s@protonmail.com>
License: MIT
License-File: LICENSE
Requires-Dist: torch
Requires-Dist: tqdm
Requires-Dist: numpy
Requires-Dist: matplotlib
